centurion_erp/conftest.py
centurion_erp/manage.py
centurion_erp/access/__init__.py
centurion_erp/access/admin.py
centurion_erp/access/apps.py
centurion_erp/access/fields.py
centurion_erp/access/urls_api.py
centurion_erp/access/functions/permissions.py
centurion_erp/access/managers/__init__.py
centurion_erp/access/managers/common.py
centurion_erp/access/managers/tenancy.py
centurion_erp/access/managers/user.py
centurion_erp/access/middleware/request.py
centurion_erp/access/migrations/0001_initial.py
centurion_erp/access/migrations/0002_alter_organization_options_alter_team_options_and_more.py
centurion_erp/access/migrations/0003_alter_team_organization_organizationnotes_teamnotes.py
centurion_erp/access/migrations/0004_organizationhistory_teamhistory.py
centurion_erp/access/migrations/0005_entity_person_entityhistory_entitynotes_role_and_more.py
centurion_erp/access/migrations/0007_rename_organization_tenant.py
centurion_erp/access/migrations/0008_alter_tenant_options_alter_entity_organization_and_more.py
centurion_erp/access/migrations/0009_migrate_organization_permission_tenant.py
centurion_erp/access/migrations/0010_company_alter_entity_entity_type_alter_person_dob_and_more.py
centurion_erp/access/migrations/0011_remove_entitynotes_model_and_more.py
centurion_erp/access/migrations/0012_centurionuser.py
centurion_erp/access/migrations/0013_role_groups_role_users.py
centurion_erp/access/migrations/0014_migrate_teams_to_role.py
centurion_erp/access/migrations/0015_remove_teamnotes_model_and_more.py
centurion_erp/access/migrations/0016_companyticket_contactticket_entityticket_and_more.py
centurion_erp/access/migrations/0017_alter_entity_organization_alter_role_organization.py
centurion_erp/access/migrations/__init__.py
centurion_erp/access/mixins/tenancy.py
centurion_erp/access/models/__init__.py
centurion_erp/access/models/centurion_user.py
centurion_erp/access/models/company_base.py
centurion_erp/access/models/contact.py
centurion_erp/access/models/entity.py
centurion_erp-1.28.1.dist-info/licenses/LICENSE
centurion_erp-1.28.1.dist-info/METADATA
centurion_erp-1.28.1.dist-info/WHEEL
centurion_erp-1.28.1.dist-info/entry_points.txt
centurion_erp-1.28.1.dist-info/top_level.txt
centurion_erp-1.28.1.dist-info/RECORD
