Metadata-Version: 2.4
Name: centurion-erp
Version: 1.28.1
Summary: An ERP with a large emphasis on the IT Service Management (ITSM) and Automation.
Author-email: No Fuss Computing <helpdesk@nofusscomputing.com>
Maintainer-email: No Fuss Computing <helpdesk@nofusscomputing.com>
License-Expression: AGPL-3.0-only
Project-URL: Documentation, https://nofusscomputing.com/projects/centurion_erp
Project-URL: Changelog, https://github.com/nofusscomputing/centurion_erp/blob/master/CHANGELOG.md
Project-URL: Homepage, https://nofusscomputing.com/projects/centurion_erp
Project-URL: Issues, https://github.com/nofusscomputing/centurion_erp/issues
Project-URL: releasenotes, https://github.com/nofusscomputing/centurion_erp/blob/master/Release-Notes.md
Project-URL: Source, https://github.com/nofusscomputing/centurion_erp
Classifier: Development Status :: 4 - Beta
Classifier: Framework :: Celery
Classifier: Framework :: Django
Classifier: Framework :: Django :: 5.1
Classifier: Intended Audience :: Developers
Classifier: Intended Audience :: Information Technology
Classifier: Intended Audience :: System Administrators
Classifier: Programming Language :: Python :: 3
Classifier: Programming Language :: Python :: 3 :: Only
Classifier: Programming Language :: Python :: 3.10
Classifier: Programming Language :: Python :: 3.11
Classifier: Programming Language :: Python :: 3.12
Classifier: Programming Language :: Python :: 3.13
Classifier: Operating System :: OS Independent
Requires-Python: >=3.10
License-File: LICENSE
Requires-Dist: amqp==5.3.1
Requires-Dist: asgiref==3.11.0
Requires-Dist: attrs==25.4.0
Requires-Dist: billiard==4.2.4
Requires-Dist: celery==5.4.0
Requires-Dist: certifi==2026.1.4
Requires-Dist: cffi==2.0.0
Requires-Dist: charset-normalizer==3.4.4
Requires-Dist: click==8.3.1
Requires-Dist: click-didyoumean==0.3.1
Requires-Dist: click-plugins==1.1.1.2
Requires-Dist: click-repl==0.3.0
Requires-Dist: coreapi==2.3.3
Requires-Dist: coreschema==0.0.4
Requires-Dist: cryptography==46.0.3
Requires-Dist: defusedxml==0.7.1
Requires-Dist: django==5.1.15
Requires-Dist: django-celery-results==2.5.1
Requires-Dist: django-cors-headers==4.4.0
Requires-Dist: django-filter==24.2
Requires-Dist: django-prometheus==2.3.1
Requires-Dist: django-split-settings==1.3.1
Requires-Dist: djangorestframework==3.16.0
Requires-Dist: djangorestframework-jsonapi==7.1.0
Requires-Dist: drf-spectacular[sidecar]==0.28.0
Requires-Dist: drf-spectacular-sidecar==2026.1.1
Requires-Dist: greenlet==3.3.0
Requires-Dist: idna==3.11
Requires-Dist: inflection==0.5.1
Requires-Dist: itypes==1.2.0
Requires-Dist: jinja2==3.1.6
Requires-Dist: jsonschema==4.26.0
Requires-Dist: jsonschema-specifications==2025.9.1
Requires-Dist: kombu==5.5.1
Requires-Dist: linkify-it-py==2.0.3
Requires-Dist: markdown-it-py[linkify,plugins]==3.0.0
Requires-Dist: markupsafe==3.0.3
Requires-Dist: mdit-py-plugins==0.5.0
Requires-Dist: mdurl==0.1.2
Requires-Dist: oauthlib==3.3.1
Requires-Dist: prometheus-client==0.21.1
Requires-Dist: prompt-toolkit==3.0.52
Requires-Dist: pycparser==3.0
Requires-Dist: pygments==2.18.0
Requires-Dist: pyjwt[crypto]==2.10.1
Requires-Dist: python-dateutil==2.9.0.post0
Requires-Dist: python3-openid==3.2.0
Requires-Dist: pytz==2025.1
Requires-Dist: pyyaml==6.0.3
Requires-Dist: referencing==0.37.0
Requires-Dist: requests==2.32.5
Requires-Dist: requests-oauthlib==2.0.0
Requires-Dist: rpds-py==0.30.0
Requires-Dist: six==1.17.0
Requires-Dist: social-auth-app-django==5.6.0
Requires-Dist: social-auth-core==4.8.3
Requires-Dist: sqlalchemy==2.0.31
Requires-Dist: sqlparse==0.5.5
Requires-Dist: typing-extensions==4.15.0
Requires-Dist: tzdata==2025.1
Requires-Dist: uc-micro-py==1.0.3
Requires-Dist: uritemplate==4.1.1
Requires-Dist: urllib3==2.6.3
Requires-Dist: vine==5.1.0
Requires-Dist: wcwidth==0.3.1
Provides-Extra: dev
Requires-Dist: amqp==5.3.1; extra == "dev"
Requires-Dist: annotated-types==0.7.0; extra == "dev"
Requires-Dist: argcomplete==3.4.0; extra == "dev"
Requires-Dist: asgiref==3.11.0; extra == "dev"
Requires-Dist: astroid==3.3.11; extra == "dev"
Requires-Dist: attrs==25.4.0; extra == "dev"
Requires-Dist: billiard==4.2.4; extra == "dev"
Requires-Dist: build==1.4.0; extra == "dev"
Requires-Dist: celery==5.4.0; extra == "dev"
Requires-Dist: certifi==2026.1.4; extra == "dev"
Requires-Dist: cffi==2.0.0; extra == "dev"
Requires-Dist: charset-normalizer==3.4.4; extra == "dev"
Requires-Dist: check-wheel-contents==0.6.3; extra == "dev"
Requires-Dist: click==8.3.1; extra == "dev"
Requires-Dist: click-didyoumean==0.3.1; extra == "dev"
Requires-Dist: click-plugins==1.1.1.2; extra == "dev"
Requires-Dist: click-repl==0.3.0; extra == "dev"
Requires-Dist: colorama==0.4.6; extra == "dev"
Requires-Dist: commitizen==3.28.0; extra == "dev"
Requires-Dist: coreapi==2.3.3; extra == "dev"
Requires-Dist: coreschema==0.0.4; extra == "dev"
Requires-Dist: coverage[toml]==7.8.0; extra == "dev"
Requires-Dist: cryptography==46.0.3; extra == "dev"
Requires-Dist: decli==0.6.3; extra == "dev"
Requires-Dist: defusedxml==0.7.1; extra == "dev"
Requires-Dist: dill==0.4.1; extra == "dev"
Requires-Dist: django==5.1.15; extra == "dev"
Requires-Dist: django-celery-results==2.5.1; extra == "dev"
Requires-Dist: django-cors-headers==4.4.0; extra == "dev"
Requires-Dist: django-debug-toolbar==5.1.0; extra == "dev"
Requires-Dist: django-filter==24.2; extra == "dev"
Requires-Dist: django-prometheus==2.3.1; extra == "dev"
Requires-Dist: django-split-settings==1.3.1; extra == "dev"
Requires-Dist: djangorestframework==3.16.0; extra == "dev"
Requires-Dist: djangorestframework-jsonapi==7.1.0; extra == "dev"
Requires-Dist: drf-spectacular[sidecar]==0.28.0; extra == "dev"
Requires-Dist: drf-spectacular-sidecar==2026.1.1; extra == "dev"
Requires-Dist: greenlet==3.3.0; extra == "dev"
Requires-Dist: gunicorn==23.0.0; extra == "dev"
Requires-Dist: idna==3.11; extra == "dev"
Requires-Dist: inflection==0.5.1; extra == "dev"
Requires-Dist: iniconfig==2.3.0; extra == "dev"
Requires-Dist: isort==6.1.0; extra == "dev"
Requires-Dist: itypes==1.2.0; extra == "dev"
Requires-Dist: jinja2==3.1.6; extra == "dev"
Requires-Dist: jsonschema==4.26.0; extra == "dev"
Requires-Dist: jsonschema-specifications==2025.9.1; extra == "dev"
Requires-Dist: kombu==5.5.1; extra == "dev"
Requires-Dist: linkify-it-py==2.0.3; extra == "dev"
Requires-Dist: markdown-it-py[linkify,plugins]==3.0.0; extra == "dev"
Requires-Dist: markupsafe==3.0.3; extra == "dev"
Requires-Dist: mccabe==0.7.0; extra == "dev"
Requires-Dist: mdit-py-plugins==0.5.0; extra == "dev"
Requires-Dist: mdurl==0.1.2; extra == "dev"
Requires-Dist: mysqlclient==2.2.4; extra == "dev"
Requires-Dist: oauthlib==3.3.1; extra == "dev"
Requires-Dist: packaging==26.0; extra == "dev"
Requires-Dist: pip-tools==7.5.2; extra == "dev"
Requires-Dist: platformdirs==4.5.1; extra == "dev"
Requires-Dist: pluggy==1.6.0; extra == "dev"
Requires-Dist: prometheus-client==0.21.1; extra == "dev"
Requires-Dist: prompt-toolkit==3.0.52; extra == "dev"
Requires-Dist: psycopg2==2.9.9; extra == "dev"
Requires-Dist: pycparser==3.0; extra == "dev"
Requires-Dist: pydantic==2.12.5; extra == "dev"
Requires-Dist: pydantic-core==2.41.5; extra == "dev"
Requires-Dist: pygments==2.18.0; extra == "dev"
Requires-Dist: pyjwt[crypto]==2.10.1; extra == "dev"
Requires-Dist: pylint==3.3.7; extra == "dev"
Requires-Dist: pyproject-hooks==1.2.0; extra == "dev"
Requires-Dist: pytest==8.3.5; extra == "dev"
Requires-Dist: pytest-cov==6.1.1; extra == "dev"
Requires-Dist: pytest-django==4.11.1; extra == "dev"
Requires-Dist: pytest-mock==3.14.0; extra == "dev"
Requires-Dist: pytest-simplified==1.0.0rc3; extra == "dev"
Requires-Dist: python-dateutil==2.9.0.post0; extra == "dev"
Requires-Dist: python3-openid==3.2.0; extra == "dev"
Requires-Dist: pytz==2025.1; extra == "dev"
Requires-Dist: pyyaml==6.0.3; extra == "dev"
Requires-Dist: questionary==2.1.1; extra == "dev"
Requires-Dist: referencing==0.37.0; extra == "dev"
Requires-Dist: requests==2.32.5; extra == "dev"
Requires-Dist: requests-oauthlib==2.0.0; extra == "dev"
Requires-Dist: rpds-py==0.30.0; extra == "dev"
Requires-Dist: six==1.17.0; extra == "dev"
Requires-Dist: social-auth-app-django==5.6.0; extra == "dev"
Requires-Dist: social-auth-core==4.8.3; extra == "dev"
Requires-Dist: sqlalchemy==2.0.31; extra == "dev"
Requires-Dist: sqlparse==0.5.5; extra == "dev"
Requires-Dist: termcolor==2.5.0; extra == "dev"
Requires-Dist: tomlkit==0.14.0; extra == "dev"
Requires-Dist: typing-extensions==4.15.0; extra == "dev"
Requires-Dist: typing-inspection==0.4.2; extra == "dev"
Requires-Dist: tzdata==2025.1; extra == "dev"
Requires-Dist: uc-micro-py==1.0.3; extra == "dev"
Requires-Dist: uritemplate==4.1.1; extra == "dev"
Requires-Dist: urllib3==2.6.3; extra == "dev"
Requires-Dist: vine==5.1.0; extra == "dev"
Requires-Dist: wcwidth==0.3.1; extra == "dev"
Requires-Dist: wheel==0.46.3; extra == "dev"
Requires-Dist: wheel-filename==1.4.2; extra == "dev"
Provides-Extra: docker
Requires-Dist: amqp==5.3.1; extra == "docker"
Requires-Dist: asgiref==3.11.0; extra == "docker"
Requires-Dist: attrs==25.4.0; extra == "docker"
Requires-Dist: billiard==4.2.4; extra == "docker"
Requires-Dist: celery==5.4.0; extra == "docker"
Requires-Dist: certifi==2026.1.4; extra == "docker"
Requires-Dist: cffi==2.0.0; extra == "docker"
Requires-Dist: charset-normalizer==3.4.4; extra == "docker"
Requires-Dist: click==8.3.1; extra == "docker"
Requires-Dist: click-didyoumean==0.3.1; extra == "docker"
Requires-Dist: click-plugins==1.1.1.2; extra == "docker"
Requires-Dist: click-repl==0.3.0; extra == "docker"
Requires-Dist: coreapi==2.3.3; extra == "docker"
Requires-Dist: coreschema==0.0.4; extra == "docker"
Requires-Dist: cryptography==46.0.3; extra == "docker"
Requires-Dist: defusedxml==0.7.1; extra == "docker"
Requires-Dist: django==5.1.15; extra == "docker"
Requires-Dist: django-celery-results==2.5.1; extra == "docker"
Requires-Dist: django-cors-headers==4.4.0; extra == "docker"
Requires-Dist: django-filter==24.2; extra == "docker"
Requires-Dist: django-prometheus==2.3.1; extra == "docker"
Requires-Dist: django-split-settings==1.3.1; extra == "docker"
Requires-Dist: djangorestframework==3.16.0; extra == "docker"
Requires-Dist: djangorestframework-jsonapi==7.1.0; extra == "docker"
Requires-Dist: drf-spectacular[sidecar]==0.28.0; extra == "docker"
Requires-Dist: drf-spectacular-sidecar==2026.1.1; extra == "docker"
Requires-Dist: greenlet==3.3.0; extra == "docker"
Requires-Dist: gunicorn==23.0.0; extra == "docker"
Requires-Dist: idna==3.11; extra == "docker"
Requires-Dist: inflection==0.5.1; extra == "docker"
Requires-Dist: itypes==1.2.0; extra == "docker"
Requires-Dist: jinja2==3.1.6; extra == "docker"
Requires-Dist: jsonschema==4.26.0; extra == "docker"
Requires-Dist: jsonschema-specifications==2025.9.1; extra == "docker"
Requires-Dist: kombu==5.5.1; extra == "docker"
Requires-Dist: linkify-it-py==2.0.3; extra == "docker"
Requires-Dist: markdown-it-py[linkify,plugins]==3.0.0; extra == "docker"
Requires-Dist: markupsafe==3.0.3; extra == "docker"
Requires-Dist: mdit-py-plugins==0.5.0; extra == "docker"
Requires-Dist: mdurl==0.1.2; extra == "docker"
Requires-Dist: mysqlclient==2.2.4; extra == "docker"
Requires-Dist: oauthlib==3.3.1; extra == "docker"
Requires-Dist: packaging==26.0; extra == "docker"
Requires-Dist: prometheus-client==0.21.1; extra == "docker"
Requires-Dist: prompt-toolkit==3.0.52; extra == "docker"
Requires-Dist: psycopg2==2.9.9; extra == "docker"
Requires-Dist: pycparser==3.0; extra == "docker"
Requires-Dist: pygments==2.18.0; extra == "docker"
Requires-Dist: pyjwt[crypto]==2.10.1; extra == "docker"
Requires-Dist: python-dateutil==2.9.0.post0; extra == "docker"
Requires-Dist: python3-openid==3.2.0; extra == "docker"
Requires-Dist: pytz==2025.1; extra == "docker"
Requires-Dist: pyyaml==6.0.3; extra == "docker"
Requires-Dist: referencing==0.37.0; extra == "docker"
Requires-Dist: requests==2.32.5; extra == "docker"
Requires-Dist: requests-oauthlib==2.0.0; extra == "docker"
Requires-Dist: rpds-py==0.30.0; extra == "docker"
Requires-Dist: six==1.17.0; extra == "docker"
Requires-Dist: social-auth-app-django==5.6.0; extra == "docker"
Requires-Dist: social-auth-core==4.8.3; extra == "docker"
Requires-Dist: sqlalchemy==2.0.31; extra == "docker"
Requires-Dist: sqlparse==0.5.5; extra == "docker"
Requires-Dist: supervisor==4.2.5; extra == "docker"
Requires-Dist: typing-extensions==4.15.0; extra == "docker"
Requires-Dist: tzdata==2025.1; extra == "docker"
Requires-Dist: uc-micro-py==1.0.3; extra == "docker"
Requires-Dist: uritemplate==4.1.1; extra == "docker"
Requires-Dist: urllib3==2.6.3; extra == "docker"
Requires-Dist: vine==5.1.0; extra == "docker"
Requires-Dist: wcwidth==0.3.1; extra == "docker"
Provides-Extra: prod
Requires-Dist: amqp==5.3.1; extra == "prod"
Requires-Dist: asgiref==3.11.0; extra == "prod"
Requires-Dist: attrs==25.4.0; extra == "prod"
Requires-Dist: billiard==4.2.4; extra == "prod"
Requires-Dist: celery==5.4.0; extra == "prod"
Requires-Dist: certifi==2026.1.4; extra == "prod"
Requires-Dist: cffi==2.0.0; extra == "prod"
Requires-Dist: charset-normalizer==3.4.4; extra == "prod"
Requires-Dist: click==8.3.1; extra == "prod"
Requires-Dist: click-didyoumean==0.3.1; extra == "prod"
Requires-Dist: click-plugins==1.1.1.2; extra == "prod"
Requires-Dist: click-repl==0.3.0; extra == "prod"
Requires-Dist: coreapi==2.3.3; extra == "prod"
Requires-Dist: coreschema==0.0.4; extra == "prod"
Requires-Dist: cryptography==46.0.3; extra == "prod"
Requires-Dist: defusedxml==0.7.1; extra == "prod"
Requires-Dist: django==5.1.15; extra == "prod"
Requires-Dist: django-celery-results==2.5.1; extra == "prod"
Requires-Dist: django-cors-headers==4.4.0; extra == "prod"
Requires-Dist: django-filter==24.2; extra == "prod"
Requires-Dist: django-prometheus==2.3.1; extra == "prod"
Requires-Dist: django-split-settings==1.3.1; extra == "prod"
Requires-Dist: djangorestframework==3.16.0; extra == "prod"
Requires-Dist: djangorestframework-jsonapi==7.1.0; extra == "prod"
Requires-Dist: drf-spectacular[sidecar]==0.28.0; extra == "prod"
Requires-Dist: drf-spectacular-sidecar==2026.1.1; extra == "prod"
Requires-Dist: greenlet==3.3.0; extra == "prod"
Requires-Dist: gunicorn==23.0.0; extra == "prod"
Requires-Dist: idna==3.11; extra == "prod"
Requires-Dist: inflection==0.5.1; extra == "prod"
Requires-Dist: itypes==1.2.0; extra == "prod"
Requires-Dist: jinja2==3.1.6; extra == "prod"
Requires-Dist: jsonschema==4.26.0; extra == "prod"
Requires-Dist: jsonschema-specifications==2025.9.1; extra == "prod"
Requires-Dist: kombu==5.5.1; extra == "prod"
Requires-Dist: linkify-it-py==2.0.3; extra == "prod"
Requires-Dist: markdown-it-py[linkify,plugins]==3.0.0; extra == "prod"
Requires-Dist: markupsafe==3.0.3; extra == "prod"
Requires-Dist: mdit-py-plugins==0.5.0; extra == "prod"
Requires-Dist: mdurl==0.1.2; extra == "prod"
Requires-Dist: mysqlclient==2.2.4; extra == "prod"
Requires-Dist: oauthlib==3.3.1; extra == "prod"
Requires-Dist: packaging==26.0; extra == "prod"
Requires-Dist: prometheus-client==0.21.1; extra == "prod"
Requires-Dist: prompt-toolkit==3.0.52; extra == "prod"
Requires-Dist: psycopg2==2.9.9; extra == "prod"
Requires-Dist: pycparser==3.0; extra == "prod"
Requires-Dist: pygments==2.18.0; extra == "prod"
Requires-Dist: pyjwt[crypto]==2.10.1; extra == "prod"
Requires-Dist: python-dateutil==2.9.0.post0; extra == "prod"
Requires-Dist: python3-openid==3.2.0; extra == "prod"
Requires-Dist: pytz==2025.1; extra == "prod"
Requires-Dist: pyyaml==6.0.3; extra == "prod"
Requires-Dist: referencing==0.37.0; extra == "prod"
Requires-Dist: requests==2.32.5; extra == "prod"
Requires-Dist: requests-oauthlib==2.0.0; extra == "prod"
Requires-Dist: rpds-py==0.30.0; extra == "prod"
Requires-Dist: six==1.17.0; extra == "prod"
Requires-Dist: social-auth-app-django==5.6.0; extra == "prod"
Requires-Dist: social-auth-core==4.8.3; extra == "prod"
Requires-Dist: sqlalchemy==2.0.31; extra == "prod"
Requires-Dist: sqlparse==0.5.5; extra == "prod"
Requires-Dist: typing-extensions==4.15.0; extra == "prod"
Requires-Dist: tzdata==2025.1; extra == "prod"
Requires-Dist: uc-micro-py==1.0.3; extra == "prod"
Requires-Dist: uritemplate==4.1.1; extra == "prod"
Requires-Dist: urllib3==2.6.3; extra == "prod"
Requires-Dist: vine==5.1.0; extra == "prod"
Requires-Dist: wcwidth==0.3.1; extra == "prod"
Dynamic: license-file
